{
    "name": "grapheme",
    "token2index": {
        "<PAD>": 0,
        "<SOS>": 1,
        "<EOS>": 2,
        "<UNK>": 3,
        "a": 4,
        "b": 5,
        "i": 6,
        "t": 7,
        "u": 8,
        "l": 9,
        "e": 10,
        "n": 11,
        "w": 12,
        "s": 13,
        "k": 14,
        "-": 15,
        "g": 16,
        "c": 17,
        "h": 18,
        "y": 19,
        "d": 20,
        "m": 21,
        "o": 22,
        "r": 23,
        "p": 24,
        "j": 25,
        "'": 26,
        " ": 27,
        "ó": 28,
        "é": 29,
        ";": 30,
        "’": 31,
        ",": 32,
        "í": 33,
        "?": 34,
        "(": 35,
        "/": 36,
        ")": 37,
        "@": 38,
        "!": 39,
        ":": 40,
        "x": 41,
        "v": 42,
        "f": 43
    },
    "index2token": {
        "0": "<PAD>",
        "1": "<SOS>",
        "2": "<EOS>",
        "3": "<UNK>",
        "4": "a",
        "5": "b",
        "6": "i",
        "7": "t",
        "8": "u",
        "9": "l",
        "10": "e",
        "11": "n",
        "12": "w",
        "13": "s",
        "14": "k",
        "15": "-",
        "16": "g",
        "17": "c",
        "18": "h",
        "19": "y",
        "20": "d",
        "21": "m",
        "22": "o",
        "23": "r",
        "24": "p",
        "25": "j",
        "26": "'",
        "27": " ",
        "28": "ó",
        "29": "é",
        "30": ";",
        "31": "’",
        "32": ",",
        "33": "í",
        "34": "?",
        "35": "(",
        "36": "/",
        "37": ")",
        "38": "@",
        "39": "!",
        "40": ":",
        "41": "x",
        "42": "v",
        "43": "f"
    },
    "n_tokens": 44
}